setup.py
wakeywakey/__init__.py
wakeywakey/app.py
wakeywakey.egg-info/PKG-INFO
wakeywakey.egg-info/SOURCES.txt
wakeywakey.egg-info/dependency_links.txt
wakeywakey.egg-info/entry_points.txt
wakeywakey.egg-info/requires.txt
wakeywakey.egg-info/top_level.txt