Metadata-Version: 1.1
Name: wakeywakey
Version: 1.0.2
Summary: Continuously mark your Slack presence as active - never appear away!
Home-page: https://github.com/angstwad/wakeywakey.git
Author: Paul Durivage
Author-email: pauldurivage+github@gmail.com
License: Apache v2.0
Platform: UNKNOWN
Classifier: Topic :: Utilities
Classifier: Topic :: Communications :: Chat
Classifier: Programming Language :: Python :: 2.6
Classifier: Programming Language :: Python :: 2.7
Classifier: Programming Language :: Python :: 3
